README.rst
setup.py
txFCM.egg-info/PKG-INFO
txFCM.egg-info/SOURCES.txt
txFCM.egg-info/dependency_links.txt
txFCM.egg-info/requires.txt
txFCM.egg-info/top_level.txt
txfcm/__init__.py
txfcm/__meta__.py
txfcm/baseapi.py
txfcm/errors.py
txfcm/txfcm.py