Metadata-Version: 1.1
Name: txFCM
Version: 0.0.1
Summary: Twisted Python client for FCM - Firebase Cloud Messaging (Android & iOS)..
Home-page: https://github.com/linteltechnologies/txfcm
Author: Godson Gera
Author-email: godson@lintelindia.com
License: MIT License
Keywords: firebase fcm apns ios gcm android push notifications
Platform: UNKNOWN
Classifier: Development Status :: 5 - Production/Stable
Classifier: Intended Audience :: Developers
Classifier: Operating System :: OS Independent
Classifier: Programming Language :: Python
Classifier: License :: OSI Approved :: MIT License
Classifier: Topic :: Communications
Classifier: Topic :: Internet
Classifier: Topic :: Software Development :: Libraries :: Python Modules
Classifier: Topic :: Utilities
Classifier: Programming Language :: Python
Classifier: Programming Language :: Python :: 2
Classifier: Programming Language :: Python :: 2.6
Classifier: Programming Language :: Python :: 2.7
